README.md
setup.py
fade/__init__.py
fade.egg-info/PKG-INFO
fade.egg-info/SOURCES.txt
fade.egg-info/dependency_links.txt
fade.egg-info/top_level.txt