Metadata-Version: 2.1
Name: fade
Version: 0.0.5
Summary: This modules allows you to fade ASCII art text with different colors.
Home-page: https://github.com/venaxyt/fade
Author: Venax
Author-email: venaxumofficial@gmail.com
License: MIT
Keywords: fade
Platform: UNKNOWN
Classifier: Development Status :: 5 - Production/Stable
Classifier: Intended Audience :: Education
Classifier: Operating System :: Microsoft :: Windows :: Windows 10
Classifier: License :: OSI Approved :: MIT License
Classifier: Programming Language :: Python :: 3.9
